AtoD-0.1.2.dist-info/DESCRIPTION.rst
AtoD-0.1.2.dist-info/METADATA
AtoD-0.1.2.dist-info/RECORD
AtoD-0.1.2.dist-info/WHEEL
AtoD-0.1.2.dist-info/metadata.json
AtoD-0.1.2.dist-info/top_level.txt
atod/__init__.py
atod/files.py
atod/meta.py
atod/settings.py
atod/data/.DS_Store
atod/data/AtoD.db
atod/data/README.md
atod/data/abilities_changes.json
atod/data/db_schemas.json
atod/data/in_game_converter.json
atod/data/loserates.csv
atod/data/matches.json
atod/data/picks.json
atod/data/players_in_matches.json
atod/data/query_to_get_matches.txt
atod/data/winrates.csv
atod/data/702/.DS_Store
atod/data/702/abilities_specs.csv
atod/data/702/abilities_texts.json
atod/data/702/db_schemas.json
atod/data/702/dota_english.txt
atod/data/702/in_game_converter.json
atod/data/702/labeled_abilities.json
atod/data/702/npc_abilities.txt
atod/data/702/npc_heroes.txt
atod/data/702/shops.txt
atod/data/706/db_schemas.json
atod/data/706/dota_english.txt
atod/data/706/in_game_converter.json
atod/data/706/labeled_abilities.json
atod/data/706/npc_abilities.txt
atod/data/706/npc_heroes.txt
atod/data/706/npc_units.txt
atod/data/706f/dota_english.txt
atod/data/706f/in_game_converter.json
atod/data/706f/labeled_abilities.json
atod/data/706f/npc_abilities.txt
atod/data/706f/npc_heroes.txt
atod/data/version-must-have/.DS_Store
atod/data/version-must-have/dota_english.txt
atod/data/version-must-have/labeled_abilities.json
atod/db/__init__.py
atod/db/content.py
atod/db/create_tables.py
atod/db/schemas.py
atod/db/setup.py
atod/db_models/__init__.py
atod/db_models/ability.py
atod/db_models/ability_specs.py
atod/db_models/ability_texts.py
atod/db_models/common_table.py
atod/db_models/hero.py
atod/db_models/patch.py
atod/models/__init__.py
atod/models/abilities.py
atod/models/ability.py
atod/models/hero.py
atod/models/heroes.py
atod/models/interfaces.py
atod/models/match.py
atod/tests/__init__.py
atod/tests/test_ability.py
atod/tests/test_cleaninng_abilities.py
atod/tests/test_dictionary.py
atod/tests/test_files.py
atod/tests/test_hero.py
atod/tests/test_hero_model.py
atod/tests/test_heroes.py
atod/tests/test_json2vectors.py
