Metadata-Version: 2.0
Name: AtoD
Version: 0.1.2
Summary: Easy access to DotA2 internal data.
Home-page: https://github.com/gasabr/AtoD
Author: Abroskin Gleb
Author-email: abroskingleb@gmail.com
License: MIT
Keywords: games data DotA2 ml
Platform: UNKNOWN
Classifier: Development Status :: 3 - Alpha
Classifier: Topic :: Games/Entertainment
Classifier: License :: OSI Approved :: MIT License
Classifier: Programming Language :: Python :: 3.5
Requires-Dist: dota2api
Requires-Dist: pandas
Requires-Dist: SQLAlchemy
Requires-Dist: yamjam
